odoo/addons/delivery_multi_destination/README.rst
odoo/addons/delivery_multi_destination/__init__.py
odoo/addons/delivery_multi_destination/__manifest__.py
odoo/addons/delivery_multi_destination/demo/delivery_carrier_demo.xml
odoo/addons/delivery_multi_destination/i18n/cs_CZ.po
odoo/addons/delivery_multi_destination/i18n/de.po
odoo/addons/delivery_multi_destination/i18n/delivery_multi_destination.pot
odoo/addons/delivery_multi_destination/i18n/es.po
odoo/addons/delivery_multi_destination/i18n/fr.po
odoo/addons/delivery_multi_destination/i18n/it.po
odoo/addons/delivery_multi_destination/i18n/nl.po
odoo/addons/delivery_multi_destination/i18n/nl_NL.po
odoo/addons/delivery_multi_destination/i18n/pt_BR.po
odoo/addons/delivery_multi_destination/i18n/sl.po
odoo/addons/delivery_multi_destination/i18n/zh_CN.po
odoo/addons/delivery_multi_destination/models/__init__.py
odoo/addons/delivery_multi_destination/models/delivery_carrier.py
odoo/addons/delivery_multi_destination/readme/CONFIGURE.rst
odoo/addons/delivery_multi_destination/readme/CONTRIBUTORS.rst
odoo/addons/delivery_multi_destination/readme/DESCRIPTION.rst
odoo/addons/delivery_multi_destination/readme/ROADMAP.rst
odoo/addons/delivery_multi_destination/readme/USAGE.rst
odoo/addons/delivery_multi_destination/static/description/icon.png
odoo/addons/delivery_multi_destination/static/description/index.html
odoo/addons/delivery_multi_destination/tests/__init__.py
odoo/addons/delivery_multi_destination/tests/test_delivery_multi_destination.py
odoo/addons/delivery_multi_destination/views/delivery_carrier_view.xml
odoo13_addon_delivery_multi_destination-13.0.1.1.3.dist-info/METADATA
odoo13_addon_delivery_multi_destination-13.0.1.1.3.dist-info/WHEEL
odoo13_addon_delivery_multi_destination-13.0.1.1.3.dist-info/top_level.txt
odoo13_addon_delivery_multi_destination-13.0.1.1.3.dist-info/RECORD
